r_logger/__init__.py
r_logger/r_logger.py
r_logger-0.1.1.dist-info/METADATA
r_logger-0.1.1.dist-info/WHEEL
r_logger-0.1.1.dist-info/top_level.txt
r_logger-0.1.1.dist-info/RECORD
