Metadata-Version: 2.1
Name: r_logger
Version: 0.1.1
Summary: a customized way to use log
Home-page: https://github.com/RaminZarebidoky/r_logger
Author: Ramin Zarebidoky
Author-email: ramin.zarebidoky@gmail.com
License: UNKNOWN
Platform: UNKNOWN
Requires-Python: >=3.7
